LICENSE.txt
README.md
setup.py
spacy_ixakat/__init__.py
spacy_ixakat/ixakat.py
spacy_ixakat.egg-info/PKG-INFO
spacy_ixakat.egg-info/SOURCES.txt
spacy_ixakat.egg-info/dependency_links.txt
spacy_ixakat.egg-info/requires.txt
spacy_ixakat.egg-info/top_level.txt
spacy_ixakat/bin/download
spacy_ixakat/bin/ixakat2conll
spacy_ixakat/bin/ixakat2ud
spacy_ixakat/bin/packages
spacy_ixakat/ixa-pipe-dep-eu/COPYING
spacy_ixakat/ixa-pipe-dep-eu/IRAKURRI
spacy_ixakat/ixa-pipe-dep-eu/README
spacy_ixakat/ixa-pipe-dep-eu/ixa-pipe-dep-eu-2.0.0-exec.jar
spacy_ixakat/ixa-pipe-dep-eu/run.sh
spacy_ixakat/ixa-pipe-pos-eu/ixa-pipe-pos-eu.sh
spacy_ixakat/ixa-pipe-pos-eu/bin/analyze
spacy_ixakat/ixa-pipe-pos-eu/bin/analyzer
spacy_ixakat/ixa-pipe-pos-eu/bin/analyzer_client
spacy_ixakat/ixa-pipe-pos-eu/bin/cg-comp
spacy_ixakat/ixa-pipe-pos-eu/bin/cg-conv
spacy_ixakat/ixa-pipe-pos-eu/bin/cg-proc
spacy_ixakat/ixa-pipe-pos-eu/bin/cg3
spacy_ixakat/ixa-pipe-pos-eu/bin/cg3-autobin.pl
spacy_ixakat/ixa-pipe-pos-eu/bin/cgflookup
spacy_ixakat/ixa-pipe-pos-eu/bin/dicc2phon
spacy_ixakat/ixa-pipe-pos-eu/bin/eustagger_lite
spacy_ixakat/ixa-pipe-pos-eu/bin/fl_initialize
spacy_ixakat/ixa-pipe-pos-eu/bin/flookup
spacy_ixakat/ixa-pipe-pos-eu/bin/foma
spacy_ixakat/ixa-pipe-pos-eu/bin/ixa-pipe-pos-eu
spacy_ixakat/ixa-pipe-pos-eu/bin/morfosintaxia_raw_swi
spacy_ixakat/ixa-pipe-pos-eu/bin/pcre++-config
spacy_ixakat/ixa-pipe-pos-eu/bin/swipl
spacy_ixakat/ixa-pipe-pos-eu/bin/swipl-ld
spacy_ixakat/ixa-pipe-pos-eu/bin/swipl-rc
spacy_ixakat/ixa-pipe-pos-eu/bin/threaded_analyzer
spacy_ixakat/ixa-pipe-pos-eu/bin/vislcg3
spacy_ixakat/ixa-pipe-pos-eu/lib/libboost_regex.so.1.53.0
spacy_ixakat/ixa-pipe-pos-eu/lib/libboost_system.so.1.53.0
spacy_ixakat/ixa-pipe-pos-eu/lib/libcg3.a
spacy_ixakat/ixa-pipe-pos-eu/lib/libcg3.so
spacy_ixakat/ixa-pipe-pos-eu/lib/libeustagger.so
spacy_ixakat/ixa-pipe-pos-eu/lib/libfoma.a
spacy_ixakat/ixa-pipe-pos-eu/lib/libfoma.so
spacy_ixakat/ixa-pipe-pos-eu/lib/libfoma.so.0
spacy_ixakat/ixa-pipe-pos-eu/lib/libfoma.so.0.9.17
spacy_ixakat/ixa-pipe-pos-eu/lib/libfreeling-3.1.so
spacy_ixakat/ixa-pipe-pos-eu/lib/libfreeling.a
spacy_ixakat/ixa-pipe-pos-eu/lib/libfreeling.la
