Metadata-Version: 2.1
Name: spacy-ixakat
Version: 0.6.9
Summary: ixaKat wrapper for spaCy
Home-page: https://github.com/KoichiYasuoka/spaCy-ixaKat
Author: Koichi Yasuoka
Author-email: yasuoka@kanji.zinbun.kyoto-u.ac.jp
License: MIT
Project-URL: ixaKat, http://ixa2.si.ehu.es/ixakat
Project-URL: Source, https://github.com/KoichiYasuoka/spaCy-ixaKat
Project-URL: Tracker, https://github.com/KoichiYasuoka/spaCy-ixaKat/issues
Keywords: ixaKat spaCy
Classifier: License :: OSI Approved :: MIT License
Classifier: Programming Language :: Python :: 3
Classifier: Operating System :: POSIX :: Linux
Classifier: Topic :: Text Processing :: Linguistic
Classifier: Natural Language :: Basque
Requires-Python: >=3.6
License-File: LICENSE.txt
